pytryfi/__init__.py
pytryfi/const.py
pytryfi/exceptions.py
pytryfi/fiBase.py
pytryfi/fiDevice.py
pytryfi/fiPet.py
pytryfi/fiUser.py
pytryfi/ledColors.py
pytryfi/common/query.py
pytryfi-0.0.21.dist-info/LICENSE
pytryfi-0.0.21.dist-info/METADATA
pytryfi-0.0.21.dist-info/WHEEL
pytryfi-0.0.21.dist-info/top_level.txt
pytryfi-0.0.21.dist-info/RECORD
